objective_weights_mcda/__init__.py
objective_weights_mcda/additions.py
objective_weights_mcda/correlations.py
objective_weights_mcda/normalizations.py
objective_weights_mcda/weighting_methods.py
objective_weights_mcda/mcda_methods/__init__.py
objective_weights_mcda/mcda_methods/aras.py
objective_weights_mcda/mcda_methods/copras.py
objective_weights_mcda/mcda_methods/mcda_method.py
objective_weights_mcda/mcda_methods/promethee.py
objective_weights_mcda/mcda_methods/vikor.py
objective_weights_mcda-0.0.12.dist-info/LICENSE
objective_weights_mcda-0.0.12.dist-info/METADATA
objective_weights_mcda-0.0.12.dist-info/WHEEL
objective_weights_mcda-0.0.12.dist-info/top_level.txt
objective_weights_mcda-0.0.12.dist-info/RECORD
