Metadata-Version: 2.1
Name: objective-weights-mcda
Version: 0.0.12
Summary: Package for Multi-Criteria Decision Analysis with Objective Criteria Weighting
Home-page: https://github.com/energyinpython/objective-weights-for-mcda
Author: Aleksandra Bączkiewicz
Author-email: aleksandra.baczkiewicz@phd.usz.edu.pl
License: UNKNOWN
Platform: UNKNOWN
Classifier: Programming Language :: Python :: 3
Classifier: License :: OSI Approved :: MIT License
Classifier: Operating System :: OS Independent
Requires-Python: >=3.4
License-File: LICENSE
Requires-Dist: numpy
